archivy_hn/__init__.py
archivy_pocket/__init__.py
archivy_hn-0.5.0.dist-info/LICENSE
archivy_hn-0.5.0.dist-info/METADATA
archivy_hn-0.5.0.dist-info/WHEEL
archivy_hn-0.5.0.dist-info/entry_points.txt
archivy_hn-0.5.0.dist-info/top_level.txt
archivy_hn-0.5.0.dist-info/RECORD
