Metadata-Version: 2.1
Name: archivy-hn
Version: 0.5.0
Summary: Archivy extension to sync upvoted posts from your hn account to your archivy instance.
Home-page: UNKNOWN
Author: Uzay-G
Author-email: halcyon@disroot.org
License: UNKNOWN
Platform: UNKNOWN
Classifier: Programming Language :: Python :: 3
Classifier: License :: OSI Approved :: MIT License
License-File: LICENSE
Requires-Dist: archivy
Requires-Dist: click
Requires-Dist: requests
Requires-Dist: bs4
Requires-Dist: lxml
Requires-Dist: html2text
